{
  "meta": {
    "title": "Next.jsで始めるモダンなブログ開発",
    "description": "Next.jsを使用してブログを構築する方法を解説します。App RouterやTypeScriptの活用方法も含めて説明します。",
    "publishedAt": "2024-01-01T00:00:00.000Z",
    "updatedAt": "2024-01-02T00:00:00.000Z",
    "tags": ["Next.js", "TypeScript", "React", "Frontend", "Web Development"]
  },
  "blocks": [
    {
      "id": "intro-1",
      "type": "text",
      "props": {
        "content": "Next.jsは、Reactベースのフルスタックフレームワークです。特にApp Routerの導入により、より直感的なルーティングが可能になりました。",
        "align": "left"
      }
    },
    {
      "id": "callout-1",
      "type": "callout",
      "props": {
        "type": "info",
        "title": "バージョンについて",
        "content": "この記事はNext.js 14を基準に解説しています。"
      }
    },
    {
      "id": "code-1",
      "type": "code",
      "props": {
        "language": "typescript",
        "fileName": "app/page.tsx",
        "code": "export default function Page() {\n  return <h1>Welcome to my blog!</h1>;\n}",
        "highlight": [2]
      }
    },
    {
      "id": "image-1",
      "type": "image",
      "props": {
        "src": "/images/nextjs-architecture.png",
        "alt": "Next.jsのアーキテクチャ図",
        "caption": "Next.jsのサーバーコンポーネントアーキテクチャ",
        "width": 800,
        "height": 600
      }
    }
  ]
}